testdep/__init__.py
testdep/coines.py
testdep/libcoines_32.dll
testdep/libcoines_64.dll
testdep/libcoines_64.so
testdep/libcoines_arm_64.dylib
testdep/libcoines_i386_64.dylib
testdep/bin/x64/api-ms-win-core-console-l1-1-0.dll
testdep/bin/x64/api-ms-win-core-console-l1-2-0.dll
testdep/bin/x64/api-ms-win-core-datetime-l1-1-0.dll
testdep/bin/x64/api-ms-win-core-debug-l1-1-0.dll
testdep/bin/x64/api-ms-win-core-errorhandling-l1-1-0.dll
testdep/bin/x64/api-ms-win-core-fibers-l1-1-0.dll
testdep/bin/x64/api-ms-win-core-file-l1-1-0.dll
testdep/bin/x64/api-ms-win-core-file-l1-2-0.dll
testdep/bin/x64/api-ms-win-core-file-l2-1-0.dll
testdep/bin/x64/api-ms-win-core-handle-l1-1-0.dll
testdep/bin/x64/api-ms-win-core-heap-l1-1-0.dll
testdep/bin/x64/api-ms-win-core-interlocked-l1-1-0.dll
testdep/bin/x64/api-ms-win-core-libraryloader-l1-1-0.dll
testdep/bin/x64/api-ms-win-core-localization-l1-2-0.dll
testdep/bin/x64/api-ms-win-core-memory-l1-1-0.dll
testdep/bin/x64/api-ms-win-core-namedpipe-l1-1-0.dll
testdep/bin/x64/api-ms-win-core-processenvironment-l1-1-0.dll
testdep/bin/x64/api-ms-win-core-processthreads-l1-1-0.dll
testdep/bin/x64/api-ms-win-core-processthreads-l1-1-1.dll
testdep/bin/x64/api-ms-win-core-profile-l1-1-0.dll
testdep/bin/x64/api-ms-win-core-rtlsupport-l1-1-0.dll
testdep/bin/x64/api-ms-win-core-string-l1-1-0.dll
testdep/bin/x64/api-ms-win-core-synch-l1-1-0.dll
testdep/bin/x64/api-ms-win-core-synch-l1-2-0.dll
testdep/bin/x64/api-ms-win-core-sysinfo-l1-1-0.dll
testdep/bin/x64/api-ms-win-core-timezone-l1-1-0.dll
testdep/bin/x64/api-ms-win-core-util-l1-1-0.dll
testdep/bin/x64/api-ms-win-crt-conio-l1-1-0.dll
testdep/bin/x64/api-ms-win-crt-convert-l1-1-0.dll
testdep/bin/x64/api-ms-win-crt-environment-l1-1-0.dll
testdep/bin/x64/api-ms-win-crt-filesystem-l1-1-0.dll
testdep/bin/x64/api-ms-win-crt-heap-l1-1-0.dll
testdep/bin/x64/api-ms-win-crt-locale-l1-1-0.dll
testdep/bin/x64/api-ms-win-crt-math-l1-1-0.dll
testdep/bin/x64/api-ms-win-crt-multibyte-l1-1-0.dll
testdep-0.0.1.dist-info/LICENSE.txt
testdep-0.0.1.dist-info/METADATA
testdep-0.0.1.dist-info/WHEEL
testdep-0.0.1.dist-info/top_level.txt
testdep-0.0.1.dist-info/RECORD
